ddOperApi/__init__.py
ddOperApi-0.9.3.dist-info/LICENSE
ddOperApi-0.9.3.dist-info/METADATA
ddOperApi-0.9.3.dist-info/WHEEL
ddOperApi-0.9.3.dist-info/top_level.txt
ddOperApi-0.9.3.dist-info/RECORD
