Metadata-Version: 2.1
Name: ddOperApi
Version: 0.9.3
Summary: Interface for the dd-oper protocol
Home-page: https://git.marceln.org/marceln/ddOperApi
Author: Marcel Nijenhof
Author-email: pypi@marceln.org
License: UNKNOWN
Platform: UNKNOWN
Classifier: Programming Language :: Python :: 3
Classifier: License :: OSI Approved :: MIT License
Classifier: Operating System :: OS Independent
Classifier: Development Status :: 4 - Beta
Requires-Python: >=3.6
License-File: LICENSE
Requires-Dist: python-dateutil
Requires-Dist: requests
Requires-Dist: numpy
Requires-Dist: pyopenssl
